jsonlinkcheck/__init__.py
jsonlinkcheck/main.py
slubjsonlinkcheck-0.9.0.dist-info/METADATA
slubjsonlinkcheck-0.9.0.dist-info/WHEEL
slubjsonlinkcheck-0.9.0.dist-info/entry_points.txt
slubjsonlinkcheck-0.9.0.dist-info/licenses/LICENSE
slubjsonlinkcheck-0.9.0.dist-info/RECORD
