Metadata-Version: 2.4
Name: slubjsonlinkcheck
Version: 0.9.0
Summary: Ein Tool zum Überprüfen und Bereinigen von URLs in JSON-Lines Dateien
Project-URL: Homepage, https://github.com/thomsbe/slubjsonlinkcheck
Project-URL: Issues, https://github.com/thomsbe/slubjsonlinkcheck/issues
Author-email: Thomas Baer <thomas.baer@slub-dresden.de>
License-Expression: MIT
License-File: LICENSE
Classifier: Development Status :: 4 - Beta
Classifier: Environment :: Console
Classifier: Intended Audience :: Developers
Classifier: License :: OSI Approved :: MIT License
Classifier: Programming Language :: Python :: 3.12
Requires-Python: >=3.12
Requires-Dist: aiofiles>=23.2.1
Requires-Dist: aiohttp>=3.9.1
Requires-Dist: tqdm>=4.66.1
